{
  "id": "shaman",
  "spells": {
    "damage_totem": {
      "x": 0,
      "y": 1
    },
    "heal_totem": {
      "x": 5,
      "y": 1
    },
    "curse_of_despair": {
      "x": 5,
      "y": 2
    },
    "curse_of_agony": {
      "x": 0,
      "y": 2
    },
    "tidal_wave": {
      "x": 10,
      "y": 0
    },
    "meteor_strike": {
      "x": 0,
      "y": 0
    },
    "venom_strike": {
      "x": 5,
      "y": 0
    },
    "curse_of_weakness": {
      "x": 10,
      "y": 2
    },
    "mana_totem": {
      "x": 10,
      "y": 1
    },
    "taunt": {
      "x": 5,
      "y": 5
    }
  },
  "lvl_reqs": [
    1,
    5,
    10,
    20,
    30,
    40,
    50
  ]
}