{
  "weight": 1000,
  "identifier": "pull",
  "attached": {
    "on_cast": [
      {
        "targets": [],
        "en_preds": [],
        "acts": [
          {
            "type": "sound",
            "map": {
              "volume": 1.0,
              "sound": "minecraft:block.anvil.hit",
              "pitch": 1.0
            }
          }
        ],
        "ifs": [
          {
            "type": "on_spell_cast",
            "map": {}
          }
        ]
      },
      {
        "targets": [
          {
            "type": "aoe",
            "map": {
              "selection_type": "RADIUS",
              "en_predicate": "enemies",
              "radius": 8.0
            }
          }
        ],
        "en_preds": [],
        "acts": [
          {
            "type": "tp_target_to_self",
            "map": {}
          },
          {
            "type": "potion",
            "map": {
              "potion_action": "GIVE_STACKS",
              "potion_id": "minecraft:slowness",
              "count": 1.0,
              "potion_dur": 100.0
            }
          },
          {
            "type": "damage",
            "map": {
              "value_calculation": "pull"
            }
          },
          {
            "type": "exile_effect",
            "map": {
              "exile_potion_id": "negative/11",
              "potion_action": "GIVE_STACKS",
              "count": 1.0,
              "potion_dur": 40.0
            }
          }
        ],
        "ifs": [
          {
            "type": "on_spell_cast",
            "map": {}
          }
        ]
      },
      {
        "targets": [],
        "en_preds": [],
        "acts": [
          {
            "type": "particles_in_radius",
            "map": {
              "particle_type": "minecraft:crit",
              "y_rand": 0.1,
              "motion": "None",
              "shape": "HORIZONTAL_CIRCLE_EDGE",
              "radius": 6.0,
              "particle_count": 100.0,
              "height": 0.5
            }
          }
        ],
        "ifs": [
          {
            "type": "on_spell_cast",
            "map": {}
          }
        ]
      }
    ],
    "entity_components": {}
  },
  "config": {
    "swing_arm": true,
    "castingWeapon": "ANY_WEAPON",
    "mana_cost": 5,
    "cooldown_ticks": 1200,
    "style": "melee",
    "tags": [
      "technique",
      "area",
      "damage"
    ],
    "cast_type": "NORMAL",
    "imbues": 1,
    "imbue_type": "ON_RANGED_ATTACK"
  },
  "disabled_dims": []
}